{
  "project_info": {
    "project_number": "329551685826",
    "project_id": "cmpai-57733",
    "storage_bucket": "cmpai-57733.appspot.com"
  },
  "client": [
    {
      "client_info": {
        "mobilesdk_app_id": "1:329551685826:android:86de9294c8489db0d8b35b",
        "android_client_info": {
          "package_name": "org.cmpai.project"
        }
      },
      "oauth_client": [],
      "api_key": [
        {
          "current_key": "AIzaSyDk6YV6U48qs0vB2lqxNEzaMFY0bBufLW8"
        }
      ],
      "services": {
        "appinvite_service": {
          "other_platform_oauth_client": []
        }
      }
    }
  ],
  "configuration_version": "1"
}